code_nav_devon-0.1.1.dist-info/METADATA
code_nav_devon-0.1.1.dist-info/WHEEL
code_nav_devon/__init__.py
code_nav_devon/code_nav_devon.abi3.so
code_nav_devon-0.1.1.dist-info/RECORD
