Metadata-Version: 2.3
Name: code_nav_devon
Version: 0.1.1
Classifier: Programming Language :: Rust
Classifier: Programming Language :: Python :: Implementation :: CPython
Classifier: Programming Language :: Python :: Implementation :: PyPy
Summary: A python package written in rust for code navigation features like text search, fuzzy search and go to definition/references
Author: arnavch04@gmail.com
Author-email: arnavch04@gmail.com
License: MIT
Requires-Python: >=3.8
